pyboy_advance/__init__.py
pyboy_advance/__main__.py
pyboy_advance/gba.py
pyboy_advance/interrupt_controller.py
pyboy_advance/keypad.py
pyboy_advance/scheduler.py
pyboy_advance/utils.py
pyboy_advance/app/__init__.py
pyboy_advance/app/window.py
pyboy_advance/cpu/__init__.py
pyboy_advance/cpu/constants.py
pyboy_advance/cpu/cpu.py
pyboy_advance/cpu/registers.py
pyboy_advance/cpu/arm/__init__.py
pyboy_advance/cpu/arm/alu.py
pyboy_advance/cpu/arm/bdt.py
pyboy_advance/cpu/arm/branch.py
pyboy_advance/cpu/arm/decode.py
pyboy_advance/cpu/arm/hwdt.py
pyboy_advance/cpu/arm/mul.py
pyboy_advance/cpu/arm/psr.py
pyboy_advance/cpu/arm/sdt.py
pyboy_advance/cpu/arm/swi.py
pyboy_advance/cpu/arm/swp.py
pyboy_advance/cpu/thumb/__init__.py
pyboy_advance/cpu/thumb/alu.py
pyboy_advance/cpu/thumb/bdt.py
pyboy_advance/cpu/thumb/branch.py
pyboy_advance/cpu/thumb/decode.py
pyboy_advance/cpu/thumb/sdt.py
pyboy_advance/cpu/thumb/swi.py
pyboy_advance/memory/__init__.py
pyboy_advance/memory/constants.py
pyboy_advance/memory/dma.py
pyboy_advance/memory/gamepak.py
pyboy_advance/memory/io.py
pyboy_advance/memory/memory.py
pyboy_advance/ppu/__init__.py
pyboy_advance/ppu/constants.py
pyboy_advance/ppu/memory.py
pyboy_advance/ppu/ppu.py
pyboy_advance/ppu/registers.py
pyboy_advance-0.0.2.dist-info/licenses/LICENSE
pyboy_advance-0.0.2.dist-info/METADATA
pyboy_advance-0.0.2.dist-info/WHEEL
pyboy_advance-0.0.2.dist-info/entry_points.txt
pyboy_advance-0.0.2.dist-info/top_level.txt
pyboy_advance-0.0.2.dist-info/RECORD
