Metadata-Version: 2.4
Name: pyboy-advance
Version: 0.0.2
Summary: Game Boy Advance emulator written in Python
Author: William Ha
Keywords: gameboy,game boy,game boy advance,gameboy advance,emulator,pypy
Classifier: Programming Language :: Python :: 3
Classifier: Programming Language :: Python :: Implementation :: PyPy
Classifier: Operating System :: OS Independent
Classifier: Topic :: System :: Emulators
Requires-Python: >=3.10
License-File: LICENSE
Requires-Dist: pysdl2
Requires-Dist: pysdl2-dll
Dynamic: license-file
